fp_common/__init__.py
fp_common/fp_types/__init__.py
fp_common/fp_types/actiontypes.py
fp_common/fp_types/apitypes.py
fp_common/fp_types/datatypes.py
fp_common/fp_types/errors.py
fp_common/fp_types/features.py
fp_common/fp_types/report_types.py
fp_common/fp_types/retypes.py
fp_common/fp_types/strategytype.py
fp_common/fp_types/task_types.py
fp_common/fp_utils/__init__.py
fp_common/fp_utils/data_utils.py
fp_common/fp_utils/func_utils.py
fp_common/fp_utils/time_utils.py
fp_common/servicecall/__init__.py
fp_common/servicecall/crawlercall.py
fp_common-1.0.6.dist-info/METADATA
fp_common-1.0.6.dist-info/WHEEL
fp_common-1.0.6.dist-info/top_level.txt
fp_common-1.0.6.dist-info/RECORD
